windows_font_manager/__init__.py
windows_font_manager/__main__.py
windows_font_manager/file_watch.py
windows_font_manager/font.py
windows_font_manager/global_val.py
windows_font_manager/static/BackFont-Regular.otf
windows_font_manager/static/favicon.ico
windows_font_manager/static/index.html
windows_font_manager/static/assets/About-BgZER52c.js
windows_font_manager/static/assets/Card-BZce44is.js
windows_font_manager/static/assets/Close-CiNIbRc7.js
windows_font_manager/static/assets/ListItem-DdoQx4f_.js
windows_font_manager/static/assets/Log-CN9vuwgW.js
windows_font_manager/static/assets/Log-U2pgU8j5.css
windows_font_manager/static/assets/Manager-BT6geCr3.js
windows_font_manager/static/assets/Manager-CMrZ_JrA.css
windows_font_manager/static/assets/Setting-Dl_coRX9.js
windows_font_manager/static/assets/Space-zbRYG9K6.js
windows_font_manager/static/assets/index-CpxkYl_T.css
windows_font_manager/static/assets/index-TSX_w_F2.js
windows_font_manager/static/assets/replaceable-BbwpPSxY.js
windows_font_manager/web/msg.py
windows_font_manager/web/server.py
windows_font_manager-0.3.7.dist-info/licenses/LICENSE
windows_font_manager-0.3.7.dist-info/METADATA
windows_font_manager-0.3.7.dist-info/WHEEL
windows_font_manager-0.3.7.dist-info/entry_points.txt
windows_font_manager-0.3.7.dist-info/top_level.txt
windows_font_manager-0.3.7.dist-info/RECORD
